polars_pf/__init__.py
polars_pf/_polars_pf.abi3.so
polars_pf/_polars_pf.pyi
polars_pf/expressions.py
polars_pf/io_source.py
polars_pf/log.py
polars_pf/perf_timer.py
polars_pf/py.typed
polars_pf/json/__init__.py
polars_pf/json/filter.py
polars_pf/json/join.py
polars_pf/json/spec.py
polars_pf-1.0.104.dist-info/METADATA
polars_pf-1.0.104.dist-info/WHEEL
polars_pf-1.0.104.dist-info/RECORD
