Metadata-Version: 2.4
Name: polars_pf
Version: 1.0.104
Classifier: Development Status :: 5 - Production/Stable
Classifier: Intended Audience :: Developers
Classifier: Operating System :: OS Independent
Classifier: Programming Language :: Python
Classifier: Programming Language :: Python :: 3
Classifier: Programming Language :: Python :: 3 :: Only
Classifier: Programming Language :: Python :: Implementation :: CPython
Classifier: Programming Language :: Python :: Implementation :: PyPy
Classifier: Programming Language :: Rust
Classifier: Typing :: Typed
Requires-Dist: msgspec>=0.19.0,<0.20.0
Requires-Dist: polars-lts-cpu>=1.33.0,<2.0.0
Requires-Dist: typing-extensions>=4.15.0,<5.0.0
Summary: PFrames - Python Polars extensions
Keywords: polars-extension
Author-email: MiLaLaboratories <support@milaboratories.com>
Maintainer-email: MiLaLaboratories <support@milaboratories.com>
Requires-Python: >=3.10
Project-URL: Homepage, https://github.com/milaboratory/pframes-rs
Project-URL: Repository, https://github.com/milaboratory/pframes-rs
Project-URL: Documentation, https://github.com/milaboratory/pframes-rs#readme
Project-URL: Bug Tracker, https://github.com/milaboratory/platforma/issues
